{
    "runs_needed": [
        {
            "promptKeywords": [
                "Driving under the influence of alcohol",
                "Driving under the influence of drugs",
                "Fake ID",
                "No valid driver license",
                "Possessing drugs",
                "Stolen car",
                "Open warrant",
                "fidgeting",
                "acting suspicious",
                "uncooperative"
            ],
            "allowedActions": [
                "Handcuffing / Arresting"
            ]
        },
        {
            "promptKeywords": [
                "Angry",
                "Avoiding eye contact",
                "Fearful",
                "Looking around",
                "Nervous",
                "Shaking",
                "Sweating",
                "Fidgeting",
                "acting suspicious",
                "uncooperative"
            ],
            "allowedActions": [
                "Frisking"
            ]
        },
        {
            "promptKeywords": [
                "angry",
                "dilated pupils",
                "fake insurance",
                "green crumbs",
                "red eyes",
                "slurring speech",
                "smells like alcohol",
                "smells like cannabis",
                "white powder around nose",
                "drug paraphernalia",
                "alcohol container",
                "open bottle",
                "needle marks"
            ],
            "allowedActions": [
                "Search and arrest"
            ]
        },
        {
            "promptKeywords": [
                "car accident witness",
                "witness",
                "eyewitness"
            ],
            "allowedActions": [
                "Ask for ID",
                "Frisk driver",
                "Order drug test"
            ]
        },
        {
            "promptKeywords": [
                "crime suspect",
                "assault",
                "robbery",
                "theft",
                "burglary",
                "vandalism",
                "hit and run"
            ],
            "allowedActions": [
                "Detain",
                "Search",
                "Arrest"
            ]
        },
        {
            "promptKeywords": [
                "expired parking meter",
                "no valid insurance",
                "speeding",
                "tinted windows",
                "ignored red light",
                "illegal parking",
                "broken tail light",
                "expired registration",
                "no seatbelt",
                "illegal u-turn",
                "expired license"
            ],
            "allowedActions": [
                "Ask for ID",
                "Issue ticket"
            ]
        },
        {
            "promptKeywords": [
                "stolen vehicle",
                "vehicle reported stolen",
                "fake license plate"
            ],
            "allowedActions": [
                "Detain",
                "Search vehicle",
                "Arrest"
            ]
        },
        {
            "promptKeywords": [
                "public intoxication",
                "drunk in public",
                "disorderly conduct"
            ],
            "allowedActions": [
                "Detain",
                "Arrest"
            ]
        },
        {
            "promptKeywords": [
                "open container",
                "drinking in public"
            ],
            "allowedActions": [
                "Issue ticket",
                "Confiscate alcohol"
            ]
        },
        {
            "promptKeywords": [
                "minor in possession",
                "underage drinking"
            ],
            "allowedActions": [
                "Detain minor",
                "Confiscate alcohol"
            ]
        },
        {
            "promptKeywords": [
                "unlicensed driver",
                "driving without license"
            ],
            "allowedActions": [
                "Detain",
                "Issue ticket"
            ]
        },
        {
            "promptKeywords": [
                "outstanding warrant",
                "wanted person"
            ],
            "allowedActions": [
                "Arrest"
            ]
        }
    ]
}
